README.rst
setup.py
celery_message_consumer.egg-info/PKG-INFO
celery_message_consumer.egg-info/SOURCES.txt
celery_message_consumer.egg-info/dependency_links.txt
celery_message_consumer.egg-info/requires.txt
celery_message_consumer.egg-info/top_level.txt
event_consumer/__about__.py
event_consumer/__init__.py
event_consumer/errors.py
event_consumer/handlers.py
event_consumer/types.py
event_consumer/conf/__init__.py
event_consumer/conf/defaults.py
event_consumer/test_utils/__init__.py
event_consumer/test_utils/handlers.py