Metadata-Version: 1.1
Name: celery-message-consumer
Version: 1.1.1
Summary: Tool for using the bin/celery worker to consume vanilla AMQP messages (i.e. not Celery tasks)
Home-page: https://github.com/depop/celery-message-consumer
Author: Depop
Author-email: dev@depop.com
License: Apache 2.0
Platform: UNKNOWN
Classifier: Environment :: Web Environment
Classifier: Intended Audience :: Developers
Classifier: License :: OSI Approved :: Apache Software License
Classifier: Operating System :: OS Independent
Classifier: Programming Language :: Python
Classifier: Programming Language :: Python :: 3.6
Classifier: Programming Language :: Python :: 2.7
